iris_pse_detection/__init__.py
iris_pse_detection/cli.py
iris_pse_detection/configuration.py
iris_pse_detection/flash.py
iris_pse_detection/flash_detection.py
iris_pse_detection/frame_data.py
iris_pse_detection/frame_rgb_converter.py
iris_pse_detection/pattern_detection.py
iris_pse_detection/py.typed
iris_pse_detection/result.py
iris_pse_detection/transition_tracker.py
iris_pse_detection/video_analyser.py
iris_pse_detection-1.1.2.dist-info/METADATA
iris_pse_detection-1.1.2.dist-info/WHEEL
iris_pse_detection-1.1.2.dist-info/entry_points.txt
iris_pse_detection-1.1.2.dist-info/licenses/LICENSE
iris_pse_detection-1.1.2.dist-info/RECORD
