Metadata-Version: 2.4
Name: iris-pse-detection
Version: 1.1.2
Summary: Python port of EA's IRIS - Photosensitive epilepsy risk detection for video content
Project-URL: Homepage, https://github.com/tokoroten/iris-pse-detection
Project-URL: Repository, https://github.com/tokoroten/iris-pse-detection
Project-URL: Original C++ Project, https://github.com/electronicarts/IRIS
Author: IRIS-PSE-Detection contributors
License: MIT
License-File: LICENSE
Keywords: accessibility,analysis,epilepsy,flash,pattern,photosensitivity,video,wcag
Classifier: Development Status :: 4 - Beta
Classifier: Intended Audience :: Developers
Classifier: License :: OSI Approved :: MIT License
Classifier: Programming Language :: Python :: 3
Classifier: Programming Language :: Python :: 3.10
Classifier: Programming Language :: Python :: 3.11
Classifier: Programming Language :: Python :: 3.12
Classifier: Programming Language :: Python :: 3.13
Classifier: Topic :: Multimedia :: Video
Classifier: Topic :: Scientific/Engineering :: Image Processing
Classifier: Typing :: Typed
Requires-Python: >=3.10
Requires-Dist: numpy>=1.22
Requires-Dist: opencv-python>=4.6
Requires-Dist: scipy>=1.8
Provides-Extra: dev
Requires-Dist: pytest-cov>=4.0; extra == 'dev'
Requires-Dist: pytest>=7.0; extra == 'dev'
Requires-Dist: ruff>=0.1.0; extra == 'dev'
